MANIFEST.in
README
setup.cfg
setup.py
medialog/.DS_Store
medialog/__init__.py
medialog.foldertextfield.egg-info/PKG-INFO
medialog.foldertextfield.egg-info/SOURCES.txt
medialog.foldertextfield.egg-info/dependency_links.txt
medialog.foldertextfield.egg-info/entry_points.txt
medialog.foldertextfield.egg-info/namespace_packages.txt
medialog.foldertextfield.egg-info/not-zip-safe
medialog.foldertextfield.egg-info/requires.txt
medialog.foldertextfield.egg-info/top_level.txt
medialog/foldertextfield/.DS_Store
medialog/foldertextfield/__init__.py
medialog/foldertextfield/config.py
medialog/foldertextfield/configure.zcml
medialog/foldertextfield/interfaces.py
medialog/foldertextfield/profiles.zcml
medialog/foldertextfield/schemaextender.py
medialog/foldertextfield/browser/__init__.py
medialog/foldertextfield/browser/configure.zcml
medialog/foldertextfield/browser/foldertextview.pt
medialog/foldertextfield/browser/foldertextview.py
medialog/foldertextfield/profiles/.DS_Store
medialog/foldertextfield/profiles/default/.DS_Store
medialog/foldertextfield/profiles/default/actions.xml
medialog/foldertextfield/profiles/default/browserlayer.xml
medialog/foldertextfield/profiles/default/metadata.xml
medialog/foldertextfield/profiles/default/types.xml
medialog/foldertextfield/profiles/default/types/.DS_Store
medialog/foldertextfield/profiles/default/types/Folder.xml