Metadata-Version: 1.1
Name: medialog.foldertextfield
Version: 0.3
Summary: Makes it possible to add a body text field to folders.
Home-page: http://products.medialog.no
Author: Grieg Medialog [Espen Moe-Nilssen]
Author-email: espen@medialog.no
License: GPL
Keywords: plone zope foldertextfield
Platform: UNKNOWN
Classifier: Framework :: Plone
Classifier: Programming Language :: Python
Classifier: Topic :: Software Development :: Libraries :: Python Modules
